wavepacket/__init__.py
wavepacket/exceptions.py
wavepacket/functions.py
wavepacket/generators.py
wavepacket/logging.py
wavepacket/builder/__init__.py
wavepacket/builder/density.py
wavepacket/builder/wave_function.py
wavepacket/expression/__init__.py
wavepacket/expression/expressionbase.py
wavepacket/expression/liouvillian.py
wavepacket/expression/schroedingerequation.py
wavepacket/grid/__init__.py
wavepacket/grid/_utils.py
wavepacket/grid/dofbase.py
wavepacket/grid/grid.py
wavepacket/grid/planewavedof.py
wavepacket/grid/spherical_harmonics_dof.py
wavepacket/grid/state.py
wavepacket/grid/state_utilities.py
wavepacket/operator/__init__.py
wavepacket/operator/fbroperators.py
wavepacket/operator/misc_operators.py
wavepacket/operator/operator_utils.py
wavepacket/operator/operatorbase.py
wavepacket/operator/potentials.py
wavepacket/operator/time_dependent_operators.py
wavepacket/plot/__init__.py
wavepacket/plot/plot_1d.py
wavepacket/solver/__init__.py
wavepacket/solver/odesolver.py
wavepacket/solver/solverbase.py
wavepacket/testing/__init__.py
wavepacket/testing/assertions.py
wavepacket/testing/dummydof.py
wavepacket/testing/dummyoperator.py
wavepacket/testing/random.py
wavepacket/typing/__init__.py
wavepacket/typing/data_types.py
wavepacket-0.2.0.dist-info/licenses/LICENSE
wavepacket-0.2.0.dist-info/WHEEL
wavepacket-0.2.0.dist-info/METADATA
wavepacket-0.2.0.dist-info/RECORD
