Metadata-Version: 2.4
Name: wavepacket
Version: 0.2.0
Summary: A package for the propagation of quantum-mechanical wave functions.
Author: Ulf Lorenz
Requires-Python: >=3.11
Classifier: License :: OSI Approved :: MIT License
Classifier: Development Status :: 3 - Alpha
Classifier: Intended Audience :: Science/Research
Classifier: Topic :: Scientific/Engineering :: Chemistry
Classifier: Topic :: Scientific/Engineering :: Physics
License-File: LICENSE
Requires-Dist: numpy >= 2.1.3
Requires-Dist: scipy >= 1.14.1
Requires-Dist: matplotlib >= 3.10
Project-URL: Home, https://github.com/ulflor/wavepacket
